{
  "name": "readline",
  "full_name": "readline",
  "tap": "homebrew/core",
  "oldnames": [],
  "aliases": [],
  "versioned_formulae": [],
  "desc": "Library for command-line editing",
  "license": "GPL-3.0-or-later",
  "homepage": "https://tiswww.case.edu/php/chet/readline/rltop.html",
  "versions": {
    "stable": "8.2.10",
    "head": null,
    "bottle": true
  },
  "urls": {
    "stable": {
      "url": "https://ftp.gnu.org/gnu/readline/readline-8.2.tar.gz",
      "tag": null,
      "revision": null,
      "using": null,
      "checksum": "3feb7171f16a84ee82ca18a36d7b9be109a52c04f492a053331d7d1095007c35"
    }
  },
  "revision": 0,
  "version_scheme": 0,
  "bottle": {
    "stable": {
      "rebuild": 0,
      "root_url": "https://ghcr.io/v2/homebrew/core",
      "files": {
        "arm64_sonoma": {
          "cellar": ":any",
          "url": "https://ghcr.io/v2/homebrew/core/readline/blobs/sha256:713fd1fa8544426b7e97eb21d13153195fea4c407db8a174bd183777b81c9192",
          "sha256": "713fd1fa8544426b7e97eb21d13153195fea4c407db8a174bd183777b81c9192"
        },
        "arm64_ventura": {
          "cellar": ":any",
          "url": "https://ghcr.io/v2/homebrew/core/readline/blobs/sha256:90351660d5ceca72a4c0a287555f2045db95f78aa5f65011b94213429f729cde",
          "sha256": "90351660d5ceca72a4c0a287555f2045db95f78aa5f65011b94213429f729cde"
        },
        "arm64_monterey": {
          "cellar": ":any",
          "url": "https://ghcr.io/v2/homebrew/core/readline/blobs/sha256:e58bc8376c36602c3cedf94075bb1097b04b77438c5a946fdbd37bf0eb6579c2",
          "sha256": "e58bc8376c36602c3cedf94075bb1097b04b77438c5a946fdbd37bf0eb6579c2"
        },
        "sonoma": {
          "cellar": ":any",
          "url": "https://ghcr.io/v2/homebrew/core/readline/blobs/sha256:9796e0ff1cc29ae7e75d8fc1a3e2c5e8ae2aeade8d9d59a16363306bf6c5b8f4",
          "sha256": "9796e0ff1cc29ae7e75d8fc1a3e2c5e8ae2aeade8d9d59a16363306bf6c5b8f4"
        },
        "ventura": {
          "cellar": ":any",
          "url": "https://ghcr.io/v2/homebrew/core/readline/blobs/sha256:952e2975dffc98bd35673c86474dbb91fadc8d993c0720e4f085597f7a484af9",
          "sha256": "952e2975dffc98bd35673c86474dbb91fadc8d993c0720e4f085597f7a484af9"
        },
        "monterey": {
          "cellar": ":any",
          "url": "https://ghcr.io/v2/homebrew/core/readline/blobs/sha256:3633320dce51662036ea90acfc9adf5bb5e6f1dca7dbdb539839736129c474b0",
          "sha256": "3633320dce51662036ea90acfc9adf5bb5e6f1dca7dbdb539839736129c474b0"
        },
        "x86_64_linux": {
          "cellar": ":any_skip_relocation",
          "url": "https://ghcr.io/v2/homebrew/core/readline/blobs/sha256:65181d2c0a9bd1d91ded6f7ec4a69b1110f65e875b332947e86a30aed7eab20f",
          "sha256": "65181d2c0a9bd1d91ded6f7ec4a69b1110f65e875b332947e86a30aed7eab20f"
        }
      }
    }
  },
  "pour_bottle_only_if": null,
  "keg_only": true,
  "keg_only_reason": {
    "reason": ":shadowed_by_macos",
    "explanation": "macOS provides BSD libedit"
  },
  "options": [],
  "build_dependencies": [],
  "dependencies": [],
  "test_dependencies": [],
  "recommended_dependencies": [],
  "optional_dependencies": [],
  "uses_from_macos": [
    "ncurses"
  ],
  "uses_from_macos_bounds": [
    {}
  ],
  "requirements": [],
  "conflicts_with": [],
  "conflicts_with_reasons": [],
  "link_overwrite": [],
  "caveats": null,
  "installed": [
    {
      "version": "8.2.10",
      "used_options": [],
      "built_as_bottle": true,
      "poured_from_bottle": true,
      "time": 1715726734,
      "runtime_dependencies": [],
      "installed_as_dependency": true,
      "installed_on_request": false
    }
  ],
  "linked_keg": null,
  "pinned": false,
  "outdated": false,
  "deprecated": false,
  "deprecation_date": null,
  "deprecation_reason": null,
  "disabled": false,
  "disable_date": null,
  "disable_reason": null,
  "post_install_defined": false,
  "service": null,
  "tap_git_head": "736dcfa3e10f73e7119619d84f81314c1abecb4d",
  "ruby_source_path": "Formula/r/readline.rb",
  "ruby_source_checksum": {
    "sha256": "ea0578c3b9a3fe562143f99089e8d6343dabfedacdcb95be0683cdc82505363e"
  },
  "variations": {},
  "analytics": {
    "install": {
      "30d": {
        "readline": 189272,
        "readline --HEAD": 19
      },
      "90d": {
        "readline": 643185,
        "readline --HEAD": 77
      },
      "365d": {
        "readline": 1848937,
        "readline --HEAD": 176
      }
    },
    "install_on_request": {
      "30d": {
        "readline": 6727,
        "readline --HEAD": 16
      },
      "90d": {
        "readline": 32931,
        "readline --HEAD": 71
      },
      "365d": {
        "readline": 101068,
        "readline --HEAD": 161
      }
    },
    "build_error": {
      "30d": {
        "readline": 8
      }
    }
  },
  "generated_date": "2024-05-27"
}
